ephemeralsrocket/__init__.py
ephemeralsrocket/connectionparams.py
ephemeralsrocket/credentials.py
ephemeralsrocket/dbmanager.py
ephemeralsrocket/ephemeralrocketdbcontext.py
ephemeralsrocket/ephemeralrocketdbcontextbuilder.py
ephemerals_rocket-1.0.3.dist-info/LICENSE.md
ephemerals_rocket-1.0.3.dist-info/METADATA
ephemerals_rocket-1.0.3.dist-info/WHEEL
ephemerals_rocket-1.0.3.dist-info/top_level.txt
ephemerals_rocket-1.0.3.dist-info/RECORD
